cranlogs/__init__.py
cranlogs/core.py
cranlogs-0.1.0.dist-info/LICENSE
cranlogs-0.1.0.dist-info/METADATA
cranlogs-0.1.0.dist-info/WHEEL
cranlogs-0.1.0.dist-info/top_level.txt
cranlogs-0.1.0.dist-info/RECORD
