Metadata-Version: 2.1
Name: cranlogs
Version: 0.1.0
Summary: CRAN download counts for R packages
Home-page: https://github.com/sophiamyang/cranlogs
Author: Sophia Man Yang
Author-email: sophimyang@gmail.com
License: BSD license
Keywords: cranlogs
Platform: UNKNOWN
Classifier: Development Status :: 2 - Pre-Alpha
Classifier: Intended Audience :: Developers
Classifier: License :: OSI Approved :: BSD License
Classifier: Natural Language :: English
Classifier: Programming Language :: Python :: 2
Classifier: Programming Language :: Python :: 2.7
Classifier: Programming Language :: Python :: 3
Classifier: Programming Language :: Python :: 3.4
Classifier: Programming Language :: Python :: 3.5
Classifier: Programming Language :: Python :: 3.6
Classifier: Programming Language :: Python :: 3.7
Requires-Dist: pandas
Requires-Dist: requests
